a_selenium_kill/LICENSE
a_selenium_kill/README.MD
a_selenium_kill/__init__.py
a_selenium_kill/requirements.txt
a_selenium_kill/thirdparty.json
a_selenium_kill-0.10.dist-info/LICENSE.rst
a_selenium_kill-0.10.dist-info/METADATA
a_selenium_kill-0.10.dist-info/WHEEL
a_selenium_kill-0.10.dist-info/top_level.txt
a_selenium_kill-0.10.dist-info/RECORD
